{"2819718": [{"username": "h", "emoji": " ", "timestamp": "2025-05-25T06:45:50.336202", "profile_pic": "profile_51_ey_ey_ron.png", "message": "hi"}, {"username": "h1", "emoji": "\ud83d\ude00", "timestamp": "2025-05-25T06:46:20.913261", "profile_pic": "default.png", "message": "hi"}, {"username": "h", "emoji": " ", "timestamp": "2025-05-25T06:48:43.164348", "profile_pic": "profile_51_ey_ey_ron.png", "message": "what"}, {"username": "h1", "emoji": "\ud83d\ude00", "timestamp": "2025-05-25T06:54:26.061676", "profile_pic": "default.png", "message": "hi"}, {"username": "h1", "emoji": "\ud83d\ude00", "timestamp": "2025-05-25T06:54:32.499937", "profile_pic": "default.png", "message": "hi"}, {"username": "h1", "emoji": "\ud83d\ude00", "timestamp": "2025-05-25T06:55:48.683151", "profile_pic": "default.png", "message": "h"}, {"username": "h", "emoji": " ", "timestamp": "2025-05-25T07:05:47.031520", "profile_pic": "profile_51_ey_ey_ron.png", "message": "hi"}, {"username": "h", "emoji": " ", "timestamp": "2025-05-25T07:05:48.444646", "profile_pic": "profile_51_ey_ey_ron.png", "message": "hi"}, {"username": "h", "emoji": " ", "timestamp": "2025-05-25T07:05:49.828685", "profile_pic": "profile_51_ey_ey_ron.png", "message": "ji"}], "1578206": [{"username": "h", "emoji": " ", "timestamp": "2025-05-25T06:49:36.208390", "profile_pic": "profile_51_ey_ey_ron.png", "message": "hi"}, {"username": "h", "emoji": " ", "timestamp": "2025-05-25T06:50:08.991149", "profile_pic": "profile_51_ey_ey_ron.png", "message": "hi"}, {"username": "h", "emoji": " ", "timestamp": "2025-05-25T06:54:15.533746", "profile_pic": "profile_51_ey_ey_ron.png", "message": "hi"}, {"username": "h", "emoji": " ", "timestamp": "2025-05-25T06:58:12.139467", "profile_pic": "profile_51_ey_ey_ron.png", "message": "hi"}, {"username": "h", "emoji": " ", "timestamp": "2025-05-25T07:01:26.130035", "profile_pic": "profile_51_ey_ey_ron.png", "message": "hi"}, {"username": "h", "emoji": " ", "timestamp": "2025-05-25T07:03:05.169327", "profile_pic": "profile_51_ey_ey_ron.png", "message": "hi"}], "8812099": [{"username": "h", "emoji": " ", "timestamp": "2025-05-25T07:18:10.915723", "profile_pic": "profile_51_ey_ey_ron.png", "message": "hi"}]}